LICENSE.txt
MANIFEST.in
README.md
setup.py
cmsplugin_oembed/__init__.py
cmsplugin_oembed/cms_plugins.py
cmsplugin_oembed/models.py
cmsplugin_oembed.egg-info/PKG-INFO
cmsplugin_oembed.egg-info/SOURCES.txt
cmsplugin_oembed.egg-info/dependency_links.txt
cmsplugin_oembed.egg-info/requires.txt
cmsplugin_oembed.egg-info/top_level.txt
cmsplugin_oembed/migrations/0001_initial.py
cmsplugin_oembed/migrations/0002_videopluginmodel_max_width.py
cmsplugin_oembed/migrations/0003_remove_videopluginmodel_name.py
cmsplugin_oembed/migrations/__init__.py
cmsplugin_oembed/static/bower_components/fitvids/jquery.fitvids.js
cmsplugin_oembed/static/bower_components/fitvids/tests.html
cmsplugin_oembed/static/cmsplugin_oembed/css/style.css
cmsplugin_oembed/templates/cmsplugin_oembed/_video.html