Metadata-Version: 1.1
Name: cmsplugin-oembed
Version: 0.1.0b6
Summary: Responsive video embedding for djangocms
Home-page: https://github.com/byteyard/djangocms_oembed
Author: Christoph Reimers
Author-email: creimers@byteyard.de
License: BSD License
Keywords: djangocms,django,responsive,oembed,video
Platform: UNKNOWN
Classifier: Operating System :: OS Independent
Classifier: Development Status :: 4 - Beta
Classifier: Programming Language :: Python
Classifier: Framework :: Django
Classifier: Programming Language :: Python :: 2.7
Classifier: Programming Language :: Python :: 3.4
